AUTHORS
CHANGELOG
ChangeLog
LICENSE
README.md
hydrant.service
hydrant.spec
requirements.txt
setup.cfg
setup.py
test-requirements.txt
tox.ini
etc/hydrant.yaml
sfhydrant/__init__.py
sfhydrant/hydrant.py
sfhydrant.egg-info/PKG-INFO
sfhydrant.egg-info/SOURCES.txt
sfhydrant.egg-info/dependency_links.txt
sfhydrant.egg-info/entry_points.txt
sfhydrant.egg-info/not-zip-safe
sfhydrant.egg-info/pbr.json
sfhydrant.egg-info/requires.txt
sfhydrant.egg-info/top_level.txt
sfhydrant/backends/__init__.py
sfhydrant/backends/base.py
sfhydrant/backends/elastic.py
sfhydrant/tests/__init__.py
sfhydrant/tests/test_hydrant.py