Metadata-Version: 1.1
Name: sfhydrant
Version: 0.1.1
Summary: firehose consumer that stores events for further retrieval
Home-page: http://softwarefactory-project.io
Author: Matthieu Huin
Author-email: softwarefactory-dev@redhat.com
License: UNKNOWN
Platform: UNKNOWN
Classifier: Intended Audience :: Information Technology
Classifier: Intended Audience :: System Administrators
Classifier: License :: OSI Approved :: Apache Software License
Classifier: Operating System :: POSIX :: Linux
Classifier: Programming Language :: Python
Classifier: Programming Language :: Python :: 2
Classifier: Programming Language :: Python :: 2.7
Classifier: Programming Language :: Python :: 3
Classifier: Programming Language :: Python :: 3.5
